AUTHORS
CHANGELOG
CONTRIBUTING.rst
INSTALL
LICENSE
MANIFEST.in
README.rst
VERSION
setup.py
hospital/__init__.py
hospital/api.py
hospital/cli.py
hospital/core.py
hospital/loading.py
hospital/pytest_plugin.py
hospital/wsgi.py
hospital.egg-info/PKG-INFO
hospital.egg-info/SOURCES.txt
hospital.egg-info/dependency_links.txt
hospital.egg-info/entry_points.txt
hospital.egg-info/not-zip-safe
hospital.egg-info/requires.txt
hospital.egg-info/top_level.txt
hospital/assertions/__init__.py
hospital/assertions/http.py
hospital/assertions/networking.py
hospital/assertions/packaging.py
hospital/healthchecks/__init__.py
hospital/healthchecks/packaging.py
hospital/healthchecks/predictable.py
hospital/utils/__init__.py
hospital/utils/networking.py
hospital/utils/packaging.py