Metadata-Version: 1.1
Name: hospital
Version: 0.8
Summary: Framework around health checks, smoke tests and diagnoses: monitor your applications and services at runtime.
Home-page: https://hospital.readthedocs.org/
Author: Benoît Bryon
Author-email: benoit@marmelune.net
License: BSD
Keywords: diagnosis healthcheck monitoring probe smoketest supervision testing
Platform: UNKNOWN
Classifier: Development Status :: 3 - Alpha
Classifier: License :: OSI Approved :: BSD License
Classifier: Programming Language :: Python :: 2.7
Classifier: Programming Language :: Python :: 3.3
Classifier: Programming Language :: Python :: 3.4
